spec_map_analysis/__init__.py
spec_map_analysis/electron_density/__init__.py
spec_map_analysis/electron_density/electron_density.py
spec_map_analysis/electron_density/line_ratio.py
spec_map_analysis/misc/__init__.py
spec_map_analysis/misc/cubik_uncertainty.py
spec_map_analysis/misc/effective_exp_time.py
spec_map_analysis/plots/__init__.py
spec_map_analysis/plots/map_plot.py
spec_map_analysis/plots/spectrum_plot.py
spec_map_analysis/reproject_convolve/__init__.py
spec_map_analysis/reproject_convolve/gauss_convol_with_corr_error.py
spec_map_analysis/reproject_convolve/reproject_convolve.py
spec_map_analysis/spectra_fitting/__init__.py
spec_map_analysis/spectra_fitting/file_reader.py
spec_map_analysis/spectra_fitting/gauss_func.py
spec_map_analysis/spectra_fitting/line_fitting.py
spec_map_analysis/spectra_fitting/line_map.py
spec_map_analysis/spectra_fitting/log_prob.py
spec_map_analysis/upper_limits/__init__.py
spec_map_analysis/upper_limits/simulated_source.py
spec_map_analysis/upper_limits/upper_limit_estimate.py
spec_map_analysis-1.1.1.dist-info/LICENSE
spec_map_analysis-1.1.1.dist-info/METADATA
spec_map_analysis-1.1.1.dist-info/WHEEL
spec_map_analysis-1.1.1.dist-info/top_level.txt
spec_map_analysis-1.1.1.dist-info/RECORD
