Metadata-Version: 2.1
Name: spec-map-analysis
Version: 1.1.1
Summary: An astronomical spectral map analysis package
Home-page: https://github.com/kjdoore/spec_map_analysis
Author: Keith Doore
Author-email: kjdoore@gmail.com
License: MIT
Platform: UNKNOWN
Classifier: Programming Language :: Python :: 3
Classifier: License :: OSI Approved :: MIT License
Classifier: Intended Audience :: Science/Research
Classifier: Topic :: Scientific/Engineering :: Astronomy
Requires-Python: >=3.6
License-File: LICENSE
Requires-Dist: numpy (>=1.20)
Requires-Dist: astropy (>=4.2)
Requires-Dist: scipy (>=1.6)
Requires-Dist: reproject (>=0.7)
Requires-Dist: PyNeb (>=1.1)
Provides-Extra: all_dep
Requires-Dist: matplotlib (>=3.3) ; extra == 'all_dep'
Requires-Dist: photutils (>=1.1) ; extra == 'all_dep'
Requires-Dist: emcee (>=3.0) ; extra == 'all_dep'
